pio/__init__.py
pio/__main__.py
pio-0.0.3.dist-info/LICENSE
pio-0.0.3.dist-info/METADATA
pio-0.0.3.dist-info/WHEEL
pio-0.0.3.dist-info/entry_points.txt
pio-0.0.3.dist-info/top_level.txt
pio-0.0.3.dist-info/RECORD
