Metadata-Version: 2.1
Name: pio
Version: 0.0.3
Summary: A simplified, yarn-like alternative to pip.
Home-page: https://github.com/Richienb/pio
Author: Richie Bendall
Author-email: richiebendall@gmail.com
License: MIT License
Platform: UNKNOWN
Classifier: Development Status :: 3 - Alpha
Classifier: Intended Audience :: Developers
Classifier: License :: OSI Approved :: MIT License
Classifier: Operating System :: OS Independent
Classifier: Natural Language :: English
Classifier: Environment :: Plugins
Classifier: Topic :: Internet
Classifier: Topic :: Software Development :: Libraries
Classifier: Programming Language :: Python
Classifier: Topic :: Software Development :: Libraries :: Python Modules
